nebula2_fork/Config.py
nebula2_fork/Exception.py
nebula2_fork/__init__.py
nebula2_fork/common/__init__.py
nebula2_fork/common/constants.py
nebula2_fork/common/ttypes.py
nebula2_fork/data/DataObject.py
nebula2_fork/data/ResultSet.py
nebula2_fork/data/__init__.py
nebula2_fork/fbthrift/TMultiplexedProcessor.py
nebula2_fork/fbthrift/TSCons.py
nebula2_fork/fbthrift/Thrift.py
nebula2_fork/fbthrift/__init__.py
nebula2_fork/fbthrift/protocol/TBinaryProtocol.py
nebula2_fork/fbthrift/protocol/TCompactProtocol.py
nebula2_fork/fbthrift/protocol/THeaderProtocol.py
nebula2_fork/fbthrift/protocol/TJSONProtocol.py
nebula2_fork/fbthrift/protocol/TMultiplexedProtocol.py
nebula2_fork/fbthrift/protocol/TProtocol.py
nebula2_fork/fbthrift/protocol/TProtocolDecorator.py
nebula2_fork/fbthrift/protocol/TSimpleJSONProtocol.py
nebula2_fork/fbthrift/protocol/__init__.py
nebula2_fork/fbthrift/protocol/exceptions.py
nebula2_fork/fbthrift/server/TAsyncioServer.py
nebula2_fork/fbthrift/server/TCppServer.py
nebula2_fork/fbthrift/server/TServer.py
nebula2_fork/fbthrift/server/__init__.py
nebula2_fork/fbthrift/transport/THeaderTransport.py
nebula2_fork/fbthrift/transport/THttpClient.py
nebula2_fork/fbthrift/transport/TSSLSocket.py
nebula2_fork/fbthrift/transport/TSSLSocketOverHttpTunnel.py
nebula2_fork/fbthrift/transport/TSocket.py
nebula2_fork/fbthrift/transport/TSocketOverHttpTunnel.py
nebula2_fork/fbthrift/transport/TSocketTest.py
nebula2_fork/fbthrift/transport/TTransport.py
nebula2_fork/fbthrift/transport/__init__.py
nebula2_fork/fbthrift/util/BytesStrIO.py
nebula2_fork/fbthrift/util/Decorators.py
nebula2_fork/fbthrift/util/Recursive.py
nebula2_fork/fbthrift/util/Serializer.py
nebula2_fork/fbthrift/util/TCppServerTestManager.py
nebula2_fork/fbthrift/util/TCppServerTestManagerTest.py
nebula2_fork/fbthrift/util/TValidator.py
nebula2_fork/fbthrift/util/__init__.py
nebula2_fork/fbthrift/util/async_common.py
nebula2_fork/fbthrift/util/asyncio.py
nebula2_fork/fbthrift/util/converter.py
nebula2_python_fork-0.0.2.dist-info/METADATA
nebula2_python_fork-0.0.2.dist-info/WHEEL
nebula2_python_fork-0.0.2.dist-info/top_level.txt
nebula2_python_fork-0.0.2.dist-info/RECORD
